launart-0.8.2.dist-info/METADATA
launart-0.8.2.dist-info/WHEEL
launart-0.8.2.dist-info/entry_points.txt
launart-0.8.2.dist-info/licenses/LICENSE
launart/__init__.py
launart/_sideload.py
launart/creator.py
launart/manager.py
launart/ryanvk/__init__.py
launart/saya.py
launart/service.py
launart/status.py
launart/utilles.py
launart-0.8.2.dist-info/RECORD
