Metadata-Version: 2.1
Name: launart
Version: 0.8.2
Summary: Component lifetime manager for runtime.
Author-Email: GreyElaina <GreyElaina@outlook.com>
License: MIT
Requires-Python: >=3.8
Requires-Dist: statv>=0.2.2
Requires-Dist: loguru>=0.6.0
Requires-Dist: creart>=0.3.0
Requires-Dist: graia-saya>=0.0.16; extra == "saya"
Provides-Extra: saya
